safe_rl/__init__.py
safe_rl-0.0.1.dist-info/LICENSE
safe_rl-0.0.1.dist-info/METADATA
safe_rl-0.0.1.dist-info/WHEEL
safe_rl-0.0.1.dist-info/top_level.txt
safe_rl-0.0.1.dist-info/RECORD
