Metadata-Version: 2.1
Name: safe-rl
Version: 0.0.1
Summary: A lib for safe RL.
Home-page: https://github.com/zhangdongkun98/safe-rl
Author: Zhang Dongkun
Author-email: zhangdongkun98@gmail.com
License: UNKNOWN
Platform: UNKNOWN
